DESCRIPTION.rst
MANIFEST.in
README.rst
setup.cfg
setup.py
zoosync/__init__.py
zoosync/version.py
zoosync/zoosync.1
zoosync/zoosync.py
zoosync.egg-info/PKG-INFO
zoosync.egg-info/SOURCES.txt
zoosync.egg-info/dependency_links.txt
zoosync.egg-info/entry_points.txt
zoosync.egg-info/requires.txt
zoosync.egg-info/top_level.txt
zoosync/scripts/zoosync.service
zoosync/scripts/zoosync.sh