Metadata-Version: 1.1
Name: zoosync
Version: 3.0.1
Summary: Zookeeper service discovery
Home-page: https://github.com/valtri/zoosync
Author: František Dvořák
Author-email: valtri@civ.zcu.cz
License: MIT
Keywords: service-discovery zookeeper cloud
Platform: UNKNOWN
Classifier: Development Status :: 3 - Alpha
Classifier: Intended Audience :: Information Technology
Classifier: Topic :: System :: Distributed Computing
Classifier: License :: OSI Approved :: MIT License
Classifier: Programming Language :: Python :: 2
Classifier: Programming Language :: Python :: 2.6
Classifier: Programming Language :: Python :: 2.7
Classifier: Programming Language :: Python :: 3
Classifier: Programming Language :: Python :: 3.2
Classifier: Programming Language :: Python :: 3.3
Classifier: Programming Language :: Python :: 3.4
